mediagoblin_hidden_original
