Metadata-Version: 1.1
Name: mediagoblin-hidden-original
Version: 0.1.4
Summary: Hide original files, show only downsized ones.
Home-page: https://gitorious.org/mediagoblin-stock/mediagoblin-hidden_original
Author: Kevin Brubeck Unhammer
Author-email: unhammer@fsfe.org
License: License :: OSI Approved :: GNU Affero General Public License v3 or later (AGPLv3+)
Download-URL: https://gitorious.org/mediagoblin-stock/mediagoblin-hidden_original/archive/mediagoblin-hidden_original-v0.1.4.tar.gz
Platform: UNKNOWN
